ipra/__init__.py
ipra/Controller/__init__.py
ipra/Controller/policyCollectionController.py
ipra/Controller/reportThreadController.py
ipra/Controller/robotThreadController.py
ipra/Logger/__init__.py
ipra/Logger/logger.py
ipra/Model/__init__.py
ipra/Model/policyCollection.py
ipra/Model/reportThread.py
ipra/Model/robotThread.py
ipra/Model/Robot/__init__.py
ipra/Model/Robot/aiaRobot.py
ipra/Model/Robot/axaRobot.py
ipra/Model/Robot/axaRobotOld.py
ipra/Model/Robot/baseRobot.py
ipra/Model/Robot/bocgRobot.py
ipra/Model/Robot/chinaLifeRobot.py
ipra/Model/Robot/chubbRobot.py
ipra/Model/Robot/cignaRobot.py
ipra/Model/Robot/fwdRobot.py
ipra/Model/Robot/generali.py
ipra/Model/Robot/manulifeRobot.py
ipra/Model/Robot/pruRobot.py
ipra/Model/Robot/sunlifeRobot.py
ipra/Model/Robot/yflifeRobot.py
ipra/Utility/ConfigUtility.py
ipra/Utility/StringUtility.py
ipra/Utility/StringUtilityCTK.py
ipra/Utility/__init__.py
ipra/Utility/tkinterUtility.py
ipra/View/__init__.py
ipra/View/editSettingTopLevel.py
ipra/View/loadingPolicyTopLevel.py
ipra/View/mainFrame.py
ipra/View/manualInputTopLevel.py
ipra/View/runningStatusFrame.py
ipra/View/runningStatusFrameCTK.py
ipra/View/test_new_main.py
ipra/View2/__init__.py
ipra/View2/aboutFrameCTK.py
ipra/View2/bootup.py
ipra/View2/bootupCTK.py
ipra/View2/checkForUpdateTopLevel.py
ipra/View2/editSettingFrameCTK.py
ipra/View2/main.py
ipra/View2/policyRobotFrame.py
ipra/View2/runningStatusFrameCTK.py
ipra/View2/sliderMenu.py
ipra/assets/__init__.py
ipra/assets/about-icon.png
ipra/assets/about-icon.png.png
ipra/assets/about-icon2.png
ipra/assets/email-icon.png
ipra/assets/group_e_icon.ico
ipra/assets/group_e_icon.png
ipra/assets/group_e_theme.json
ipra/assets/hexicon.ico
ipra/assets/home_dark.png
ipra/assets/home_light.png
ipra/assets/reports-icon.png
ipra/assets/reports-icon2.png
ipra/assets/setting-icon.png
ipra/assets/setting-icon2.png
IPRA_SESG-3.20.51.dist-info/METADATA
IPRA_SESG-3.20.51.dist-info/WHEEL
IPRA_SESG-3.20.51.dist-info/top_level.txt
IPRA_SESG-3.20.51.dist-info/RECORD
