Metadata-Version: 2.1
Name: IPRA-SESG
Version: 3.20.51
Summary: GUI Application
Home-page: 
Author: HexBee
Author-email: mat230821@hotmail.com
Classifier: Programming Language :: Python :: 3
Classifier: License :: OSI Approved :: MIT License
Classifier: Operating System :: OS Independent
Requires-Python: >=3.5
